<?xml version="1.0" encoding="utf-8" ?><dwsync><file name="PrintPress.jpg" server="185.53.173.97/public_html/" local="3521540204" remote="3521544120" Dst="-1" /><file name="strategy.jpg" server="185.53.173.97/public_html/" local="3521540204" remote="3521544120" Dst="-1" /><file name="Video.jpg" server="185.53.173.97/public_html/" local="3521540204" remote="3521544120" Dst="-1" /><file name=".DS_Store" server="185.53.173.97/public_html/" local="3521618181" remote="3521533020" Dst="-1" /><file name="Branding.jpg" server="185.53.173.97/public_html/" local="3521618182" remote="3521542020" Dst="-1" /><file name="IndigoRiver_Logo_Black-01.svg" server="185.53.173.97/public_html/" local="3521618182" remote="3521461080" Dst="-1" /><file name="Bobbi_mac.png" server="185.53.173.97/public_html/" local="3521618182" remote="3521542080" Dst="-1" /><file name="Contact_BG.jpg" server="185.53.173.97/public_html/" local="3521618182" remote="3521542140" Dst="-1" /><file name="IndigoRiver_Logo_White-01.svg" server="185.53.173.97/public_html/" local="3521618183" remote="3521461080" Dst="-1" /><file name="accreditations.png" server="185.53.173.97/public_html/" local="3521618183" remote="3521542020" Dst="-1" /><file name="accreditations2.png" server="185.53.173.97/public_html/" local="3521618183" remote="3521542020" Dst="-1" /><file name="arrowDown.png" server="185.53.173.97/public_html/" local="3521618183" remote="3521542020" Dst="-1" /><file name="contactHeader.jpg" server="185.53.173.97/public_html/" local="3521618187" remote="3521542080" Dst="-1" /><file name="digital.jpg" server="185.53.173.97/public_html/" local="3521618188" remote="3521542080" Dst="-1" /><file name="digital-image.jpg" server="185.53.173.97/public_html/" local="3521618190" remote="3521542140" Dst="-1" /><file name="events image.jpeg" server="185.53.173.97/public_html/" local="3521618190" remote="3521542140" Dst="-1" /><file name="gravatar.jpg" server="185.53.173.97/public_html/" local="3521618190" remote="3521461020" Dst="-1" /><file name="events-image.jpeg" server="185.53.173.97/public_html/" local="3521618191" remote="3521461020" Dst="-1" /><file name="events.jpg" server="185.53.173.97/public_html/" local="3521618191" remote="3521461020" Dst="-1" /><file name="home-slider-branding-2.png" server="185.53.173.97/public_html/" local="3521618192" remote="3521461020" Dst="-1" /><file name="home-slider-branding2.png" server="185.53.173.97/public_html/" local="3521618192" remote="3521461020" Dst="-1" /><file name="home-slider-branding.png" server="185.53.173.97/public_html/" local="3521618193" remote="3521461020" Dst="-1" /><file name="home-slider-printpress.jpg" server="185.53.173.97/public_html/" local="3521618195" remote="3521461080" Dst="-1" /><file name="home-slider-events.png" server="185.53.173.97/public_html/" local="3521618195" remote="3521461140" Dst="-1" /><file name="home-slider-strategy.jpg" server="185.53.173.97/public_html/" local="3521618196" remote="3521461080" Dst="-1" /><file name="home-slider-test.jpg" server="185.53.173.97/public_html/" local="3521618197" remote="3521461080" Dst="-1" /><file name="home-slider-video.png" server="185.53.173.97/public_html/" local="3521618198" remote="3521461080" Dst="-1" /><file name="locate.png" server="185.53.173.97/public_html/" local="3521618200" remote="3521461080" Dst="-1" /><file name="logo.svg" server="185.53.173.97/public_html/" local="3521618200" remote="3521461080" Dst="-1" /><file name="logo.png" server="185.53.173.97/public_html/" local="3521618200" remote="3521461080" Dst="-1" /><file name="plus.png" server="185.53.173.97/public_html/" local="3521618211" remote="3521461260" Dst="-1" /><file name="strategy-slide.png" server="185.53.173.97/public_html/" local="3521618212" remote="3521461320" Dst="-1" /><file name="work-Multi-Comfort.jpg" server="185.53.173.97/public_html/" local="3521618214" remote="3521461320" Dst="-1" /><file name="work-Schluter.jpg" server="185.53.173.97/public_html/" local="3521618215" remote="3521461380" Dst="-1" /><file name="work-USN.jpg" server="185.53.173.97/public_html/" local="3521618216" remote="3521461320" Dst="-1" /><file name="work-Places.png" server="185.53.173.97/public_html/" local="3521618217" remote="3521461380" Dst="-1" /><file name="work-Weber-Congress.png" server="185.53.173.97/public_html/" local="3521618217" remote="3521461380" Dst="-1" /><file name="workHeader.png" server="185.53.173.97/public_html/" local="3521618218" remote="3521461380" Dst="-1" /></dwsync>